faux_data/__init__.py
faux_data/cmd.py
faux_data/column.py
faux_data/config.py
faux_data/factory.py
faux_data/main.py
faux_data/table.py
faux_data/target.py
faux_data/template.py
faux_data/template_rendering.py
faux_data/utils.py
faux_data/version.py
faux_data/templates/help.jinja
faux_data/templates/render.jinja
faux_data/templates/run.jinja
faux_data/templates/sample.jinja
faux_data-0.0.18.dist-info/LICENSE.txt
faux_data-0.0.18.dist-info/METADATA
faux_data-0.0.18.dist-info/WHEEL
faux_data-0.0.18.dist-info/entry_points.txt
faux_data-0.0.18.dist-info/top_level.txt
faux_data-0.0.18.dist-info/RECORD
