Metadata-Version: 2.1
Name: faux-data
Version: 0.0.18
Summary: Generate fake data from yaml templates
Home-page: UNKNOWN
Author: jack-tee
Author-email: 10283360+jack-tee@users.noreply.github.com
License: UNKNOWN
Platform: UNKNOWN
Classifier: Development Status :: 4 - Beta
Classifier: Programming Language :: Python :: 3 :: Only
Classifier: Programming Language :: Python :: 3.10
Classifier: License :: OSI Approved :: Apache Software License
License-File: LICENSE.txt
Requires-Dist: pandas (==1.4.2)
Requires-Dist: google-cloud-bigquery
Requires-Dist: google-cloud-pubsub
Requires-Dist: pyarrow
Requires-Dist: pyyaml
Requires-Dist: jinja2
Requires-Dist: tabulate
Requires-Dist: fsspec
Requires-Dist: gcsfs
Requires-Dist: dynaconf
